jsonschema_specifications/__init__.py
jsonschema_specifications/_core.py
jsonschema_specifications/schemas/draft201909/metaschema.json
jsonschema_specifications/schemas/draft201909/vocabularies/applicator
jsonschema_specifications/schemas/draft201909/vocabularies/content
jsonschema_specifications/schemas/draft201909/vocabularies/core
jsonschema_specifications/schemas/draft201909/vocabularies/meta-data
jsonschema_specifications/schemas/draft201909/vocabularies/validation
jsonschema_specifications/schemas/draft202012/metaschema.json
jsonschema_specifications/schemas/draft202012/vocabularies/applicator
jsonschema_specifications/schemas/draft202012/vocabularies/content
jsonschema_specifications/schemas/draft202012/vocabularies/core
jsonschema_specifications/schemas/draft202012/vocabularies/format
jsonschema_specifications/schemas/draft202012/vocabularies/format-annotation
jsonschema_specifications/schemas/draft202012/vocabularies/format-assertion
jsonschema_specifications/schemas/draft202012/vocabularies/meta-data
jsonschema_specifications/schemas/draft202012/vocabularies/unevaluated
jsonschema_specifications/schemas/draft202012/vocabularies/validation
jsonschema_specifications/schemas/draft3/metaschema.json
jsonschema_specifications/schemas/draft4/metaschema.json
jsonschema_specifications/schemas/draft6/metaschema.json
jsonschema_specifications/schemas/draft7/metaschema.json
jsonschema_specifications/tests/test_jsonschema_specifications.py
jsonschema_specifications-2023.5.2.dist-info/METADATA
jsonschema_specifications-2023.5.2.dist-info/WHEEL
jsonschema_specifications-2023.5.2.dist-info/licenses/COPYING
jsonschema_specifications-2023.5.2.dist-info/RECORD
