Metadata-Version: 2.1
Name: jsonschema-specifications
Version: 2023.5.2
Summary: The JSON Schema meta-schemas and vocabularies, exposed as a Registry
Project-URL: Documentation, https://jsonschema-specifications.readthedocs.io/
Project-URL: Homepage, https://github.com/python-jsonschema/jsonschema-specifications
Project-URL: Issues, https://github.com/python-jsonschema/jsonschema-specifications/issues/
Project-URL: Funding, https://github.com/sponsors/Julian
Project-URL: Source, https://github.com/python-jsonschema/jsonschema-specifications
Author: Julian Berman
Author-email: Julian+jsonschema-specifications@GrayVines.com
License: MIT
License-File: COPYING
Keywords: data validation,json,json schema,jsonschema,validation
Classifier: Development Status :: 5 - Production/Stable
Classifier: License :: OSI Approved :: MIT License
Classifier: Operating System :: OS Independent
Classifier: Programming Language :: Python
Classifier: Programming Language :: Python :: 3.8
Classifier: Programming Language :: Python :: 3.9
Classifier: Programming Language :: Python :: 3.10
Classifier: Programming Language :: Python :: 3.11
Classifier: Programming Language :: Python :: Implementation :: CPython
Classifier: Programming Language :: Python :: Implementation :: PyPy
Classifier: Topic :: File Formats :: JSON :: JSON Schema
Requires-Python: >=3.8
Requires-Dist: importlib-resources>=1.4.0; python_version < '3.9'
Requires-Dist: referencing>=0.28.0
